linkinglines/ClusterLines.py
linkinglines/DilationCalculations.py
linkinglines/ExamineClusters.py
linkinglines/FitRadialCenters.py
linkinglines/FitRectangle.py
linkinglines/HT.py
linkinglines/PlotUtils.py
linkinglines/PrePostProcess.py
linkinglines/SyntheticLines.py
linkinglines/__init__.py
linkinglines/__main__.py
linkinglines-2.1.2.dist-info/AUTHORS
linkinglines-2.1.2.dist-info/LICENSE
linkinglines-2.1.2.dist-info/METADATA
linkinglines-2.1.2.dist-info/WHEEL
linkinglines-2.1.2.dist-info/RECORD
