Metadata-Version: 2.1
Name: linkinglines
Version: 2.1.2
Summary: Process linear geospatial data and link them using the Hough Transform and Agglomerative Clustering
Home-page: https://github.com/aikubo/LinkingLines
License: MIT
Keywords: geospatial,houghtransform,clustering
Author: aikubo
Author-email: alli.i.kubo@gmail.com
Requires-Python: >=3.10,<4.0
Classifier: License :: OSI Approved :: MIT License
Classifier: Programming Language :: Python :: 3
Classifier: Programming Language :: Python :: 3.10
Classifier: Programming Language :: Python :: 3.11
Classifier: Programming Language :: Python :: 3.12
Requires-Dist: geopandas (>=0.14.3,<0.15.0)
Requires-Dist: matplotlib (>=3.8.3,<4.0.0)
Requires-Dist: matplotlib-label-lines (>=0.7.0,<0.8.0)
Requires-Dist: numpy (>=1.26.4,<2.0.0)
Requires-Dist: pandas (>=2.2.1,<3.0.0)
Requires-Dist: scikit-learn (>=1.4.1.post1,<2.0.0)
Requires-Dist: scipy (>=1.12.0,<2.0.0)
Requires-Dist: seaborn (>=0.13.2,<0.14.0)
Requires-Dist: statsmodels (>=0.14.1,<0.15.0)
Project-URL: Documentation, https://linkinglines.readthedocs.io/en/latest/
Project-URL: Repository, https://github.com/aikubo/LinkingLines
